{
    "32": {
        "0": {
            "sn": "05369",
            "brief": "尼珥"
        },
        "1": {
            "sn": "03205",
            "brief": "生出、出生"
        },
        "literal": "尼珥生基士；而基士生扫罗；而扫罗生约拿单、和麦基・舒亚、和亚比拿达、和伊施巴力。",
        "2": {
            "sn": "00853",
            "brief": "不必翻译"
        },
        "3": {
            "sn": "07027",
            "brief": "基士"
        },
        "4": {
            "sn": "07027",
            "brief": "基士"
        },
        "6": {
            "sn": "00853",
            "brief": "不必翻译"
        },
        "7": {
            "sn": "07586",
            "brief": "扫罗"
        },
        "8": {
            "sn": "07586",
            "brief": "扫罗"
        },
        "10": {
            "sn": "00853",
            "brief": "不必翻译"
        },
        "11": {
            "sn": "03083",
            "brief": "约拿单"
        },
        "12": {
            "sn": "00853",
            "brief": "不必翻译"
        },
        "13": {
            "sn": "04444",
            "brief": "麦基•舒亚"
        },
        "14": {
            "sn": "04444",
            "brief": "麦基•舒亚"
        },
        "15": {
            "sn": "00853",
            "brief": "不必翻译"
        },
        "16": {
            "sn": "00041",
            "brief": "亚比拿达"
        },
        "17": {
            "sn": "00853",
            "brief": "不必翻译"
        },
        "18": {
            "sn": "00792",
            "brief": "伊施巴力"
        },
        "5": {
            "sn": "03205",
            "brief": "生出、出生"
        },
        "9": {
            "sn": "03205",
            "brief": "生出、出生"
        }
    },
    "33": {
        "0": {
            "sn": "01121",
            "brief": "儿子、孙子、后裔、成员"
        },
        "literal": "约拿单的儿子是米力・巴力；米力・巴力生弥迦。",
        "1": {
            "sn": "03083",
            "brief": "约拿单"
        },
        "2": {
            "sn": "04807",
            "brief": "米力・巴力"
        },
        "3": {
            "sn": "04807",
            "brief": "米力・巴力"
        },
        "4": {
            "sn": "04807",
            "brief": "米力・巴力"
        },
        "5": {
            "sn": "04807",
            "brief": "米力・巴力"
        },
        "7": {
            "sn": "00853",
            "brief": "不必翻译"
        },
        "8": {
            "sn": "04318",
            "brief": "弥迦"
        },
        "9": {
            "sn": "09014",
            "brief": "关闭的意思"
        },
        "6": {
            "sn": "03205",
            "brief": "生出、出生"
        }
    },
    "29": {
        "literal": "他的长子是亚伯顿。(接着有)苏珥、和基士、和巴力、和拿答、",
        "0": {
            "sn": "01121",
            "brief": "儿子、孙子、后裔、成员"
        },
        "1": {
            "sn": "01060",
            "brief": "头生的、长子"
        },
        "2": {
            "sn": "05658",
            "brief": "亚伯顿"
        },
        "3": {
            "sn": "06698",
            "brief": "苏珥"
        },
        "4": {
            "sn": "07027",
            "brief": "基士"
        },
        "5": {
            "sn": "01168",
            "brief": "巴力"
        },
        "6": {
            "sn": "05070",
            "brief": "拿答"
        }
    },
    "30": {
        "literal": "和基多、和亚希约、和撒迦。",
        "0": {
            "sn": "01446",
            "brief": "基多"
        },
        "1": {
            "sn": "00283",
            "brief": "亚希约"
        },
        "2": {
            "sn": "02144",
            "brief": "撒迦"
        }
    },
    "27": {
        "literal": "这些是他们家谱里家族的首领，这些首领(都)住在耶路撒冷。",
        "0": {
            "sn": "00428",
            "brief": "这些"
        },
        "1": {
            "sn": "07218",
            "brief": "头、起头、山顶、领袖"
        },
        "2": {
            "sn": "00001",
            "brief": "父亲、祖先"
        },
        "3": {
            "sn": "08435",
            "brief": "子孙、后代、家谱"
        },
        "4": {
            "sn": "07218",
            "brief": "头、起头、山顶、领袖"
        },
        "6": {
            "sn": "03427",
            "brief": "居住、坐、停留"
        },
        "7": {
            "sn": "03389",
            "brief": "耶路撒冷"
        },
        "8": {
            "sn": "09014",
            "brief": "关闭的意思"
        },
        "5": {
            "sn": "00428",
            "brief": "这些"
        }
    },
    "38": {
        "1": {
            "sn": "06232",
            "brief": "以设"
        },
        "2": {
            "sn": "00251",
            "brief": "兄弟、弟兄"
        },
        "3": {
            "sn": "00198",
            "brief": "乌兰"
        },
        "5": {
            "sn": "03266",
            "brief": "耶乌施"
        },
        "literal": "他(指亚悉)兄弟以设的儿子：长子乌兰，次子耶乌施，和三子以利法列。",
        "0": {
            "sn": "01121",
            "brief": "儿子、孙子、后裔、成员"
        },
        "4": {
            "sn": "01060",
            "brief": "头生的、长子"
        },
        "6": {
            "sn": "08145",
            "brief": "序数的第二"
        },
        "7": {
            "sn": "00467",
            "brief": "以利法列"
        },
        "8": {
            "sn": "07992",
            "brief": "序数的「第三」"
        }
    },
    "26": {
        "literal": "和雅利西、和以利亚、和细基利(都)是耶罗罕的儿子。",
        "0": {
            "sn": "03298",
            "brief": "雅利西"
        },
        "1": {
            "sn": "00452",
            "brief": "以利亚"
        },
        "2": {
            "sn": "02147",
            "brief": "细基利"
        },
        "3": {
            "sn": "01121",
            "brief": "儿子、孙子、后裔、成员"
        },
        "4": {
            "sn": "03395",
            "brief": "耶罗罕"
        }
    },
    "7": {
        "0": {
            "sn": "07842",
            "brief": "沙哈连"
        },
        "2": {
            "sn": "07704",
            "brief": "田地"
        },
        "3": {
            "sn": "04124",
            "brief": "摩押"
        },
        "4": {
            "sn": "04480",
            "brief": "从"
        },
        "5": {
            "sn": "07971",
            "brief": "差遣、释放、送走、伸出、伸展"
        },
        "6": {
            "sn": "00853",
            "brief": "不必翻译"
        },
        "7": {
            "sn": "02366",
            "brief": "户伸"
        },
        "8": {
            "sn": "00853",
            "brief": "不必翻译"
        },
        "literal": "沙哈连…在摩押地生了(儿子)。(…处填入下行)在休了他们，即他的妻子户伸和巴拉之后，",
        "9": {
            "sn": "01199",
            "brief": "巴拉"
        },
        "10": {
            "sn": "00802",
            "brief": "女人、妻子"
        },
        "1": {
            "sn": "03205",
            "brief": "生出、出生"
        }
    },
    "9": {
        "0": {
            "sn": "00853",
            "brief": "不必翻译"
        },
        "1": {
            "sn": "03263",
            "brief": "耶乌斯"
        },
        "9": {
            "sn": "00001",
            "brief": "父亲、祖先"
        },
        "literal": "和耶乌斯、和沙迦、和米玛。这些(都)是他的儿子，是家族的族长。",
        "2": {
            "sn": "00853",
            "brief": "不必翻译"
        },
        "3": {
            "sn": "07634",
            "brief": "沙迦"
        },
        "4": {
            "sn": "00853",
            "brief": "不必翻译"
        },
        "5": {
            "sn": "04821",
            "brief": "米玛"
        },
        "6": {
            "sn": "00428",
            "brief": "这些"
        },
        "7": {
            "sn": "01121",
            "brief": "儿子、孙子、后裔、成员"
        },
        "8": {
            "sn": "07218",
            "brief": "头、起头、山顶、领袖"
        }
    },
    "11": {
        "6": {
            "sn": "01129",
            "brief": "建造"
        },
        "7": {
            "sn": "00853",
            "brief": "不必翻译"
        },
        "8": {
            "sn": "00207",
            "brief": "阿挪"
        },
        "9": {
            "sn": "00853",
            "brief": "不必翻译"
        },
        "10": {
            "sn": "03850",
            "brief": "罗德"
        },
        "11": {
            "sn": "01323",
            "brief": "女儿、女子、村庄"
        },
        "literal": "以利巴力的儿子是希伯、和米珊、和沙麦(他建立阿挪和罗德与其村庄)、",
        "0": {
            "sn": "01121",
            "brief": "儿子、孙子、后裔、成员"
        },
        "1": {
            "sn": "00508",
            "brief": "以利巴力"
        },
        "2": {
            "sn": "05677",
            "brief": "希伯"
        },
        "3": {
            "sn": "04936",
            "brief": "米珊"
        },
        "4": {
            "sn": "08106",
            "brief": "沙麦"
        },
        "5": {
            "sn": "01931",
            "brief": "他"
        }
    },
    "20": {
        "0": {
            "sn": "05718",
            "brief": "亚大雅"
        },
        "1": {
            "sn": "01256",
            "brief": "比拉雅"
        },
        "literal": "和亚大雅、和比拉雅、和申拉(都)是示每的儿子。",
        "2": {
            "sn": "08119",
            "brief": "申拉"
        },
        "3": {
            "sn": "01121",
            "brief": "儿子、孙子、后裔、成员"
        },
        "4": {
            "sn": "08096",
            "brief": "示每"
        }
    },
    "0": {
        "literal": "便雅悯生了他的长子比拉，次子亚实别，和三子亚哈拉，",
        "0": {
            "sn": "01144",
            "brief": "便雅悯"
        },
        "2": {
            "sn": "00853",
            "brief": "不必翻译"
        },
        "3": {
            "sn": "01106",
            "brief": "比拉"
        },
        "4": {
            "sn": "01060",
            "brief": "头生的、长子"
        },
        "5": {
            "sn": "00788",
            "brief": "亚实别"
        },
        "6": {
            "sn": "08145",
            "brief": "序数的第二"
        },
        "7": {
            "sn": "00315",
            "brief": "亚哈拉"
        },
        "8": {
            "sn": "07992",
            "brief": "序数的「第三」"
        },
        "1": {
            "sn": "03205",
            "brief": "生出、出生"
        }
    },
    "3": {
        "literal": "和亚比书、和乃幔、和亚何亚、",
        "0": {
            "sn": "00050",
            "brief": "亚比书"
        },
        "1": {
            "sn": "05283",
            "brief": "乃缦"
        },
        "2": {
            "sn": "00265",
            "brief": "亚何亚"
        }
    },
    "5": {
        "2": {
            "sn": "00261",
            "brief": "以忽"
        },
        "3": {
            "sn": "00428",
            "brief": "这些"
        },
        "literal": "这些是以忽的儿子，这些人他们是迦巴居民的族长，他们把他们掳到玛拿辖：",
        "0": {
            "sn": "00428",
            "brief": "这些"
        },
        "1": {
            "sn": "01121",
            "brief": "儿子、孙子、后裔、成员"
        },
        "4": {
            "sn": "01992",
            "brief": "他们、它们"
        },
        "5": {
            "sn": "07218",
            "brief": "头、起头、山顶、领袖"
        },
        "6": {
            "sn": "00001",
            "brief": "父亲、祖先"
        },
        "7": {
            "sn": "03427",
            "brief": "居住、坐、停留"
        },
        "8": {
            "sn": "01387",
            "brief": "迦巴"
        },
        "10": {
            "sn": "00413",
            "brief": "向、往"
        },
        "11": {
            "sn": "04506",
            "brief": "玛拿辖"
        },
        "9": {
            "sn": "01540",
            "brief": "显露、揭开、移除、迁移"
        }
    },
    "22": {
        "0": {
            "sn": "05658",
            "brief": "亚伯顿"
        },
        "1": {
            "sn": "02147",
            "brief": "细基利"
        },
        "2": {
            "sn": "02605",
            "brief": "哈难"
        },
        "literal": "和亚伯顿、和细基利、和哈难、"
    },
    "28": {
        "2": {
            "sn": "00001",
            "brief": "父亲、祖先"
        },
        "3": {
            "sn": "01391",
            "brief": "基遍"
        },
        "literal": "在基遍住的有基遍的父亲，他的妻子的名字是玛迦；",
        "0": {
            "sn": "01391",
            "brief": "基遍"
        },
        "1": {
            "sn": "03427",
            "brief": "居住、坐、停留"
        },
        "4": {
            "sn": "08034",
            "brief": "名字"
        },
        "5": {
            "sn": "00802",
            "brief": "女人、妻子"
        },
        "6": {
            "sn": "04601",
            "brief": "玛迦"
        }
    },
    "31": {
        "7": {
            "sn": "00251",
            "brief": "兄弟、弟兄"
        },
        "literal": "米基罗生示米暗。而他们对着他们的弟兄，…居住在耶路撒冷。(…处填入下行)和他们的弟兄一起",
        "0": {
            "sn": "04732",
            "brief": "米基罗"
        },
        "2": {
            "sn": "00853",
            "brief": "不必翻译"
        },
        "3": {
            "sn": "08039",
            "brief": "示米暗"
        },
        "4": {
            "sn": "00637",
            "brief": "的确、也"
        },
        "5": {
            "sn": "01992",
            "brief": "他们、它们"
        },
        "6": {
            "sn": "05048",
            "brief": "在…面前"
        },
        "8": {
            "sn": "03427",
            "brief": "居住、坐、停留"
        },
        "9": {
            "sn": "03389",
            "brief": "耶路撒冷"
        },
        "1": {
            "sn": "03205",
            "brief": "生出、出生"
        },
        "10": {
            "sn": "05973",
            "brief": "跟"
        },
        "11": {
            "sn": "00251",
            "brief": "兄弟、弟兄"
        },
        "12": {
            "sn": "09014",
            "brief": "关闭的意思"
        }
    },
    "16": {
        "literal": "而西巴第雅、和米书兰、和希西基、和希百、",
        "0": {
            "sn": "02069",
            "brief": "西巴第雅"
        },
        "1": {
            "sn": "04918",
            "brief": "米书兰"
        },
        "2": {
            "sn": "02395",
            "brief": "希西基"
        },
        "3": {
            "sn": "02268",
            "brief": "希百"
        }
    },
    "8": {
        "1": {
            "sn": "04480",
            "brief": "从"
        },
        "2": {
            "sn": "02321",
            "brief": "贺得"
        },
        "3": {
            "sn": "00802",
            "brief": "女人、妻子"
        },
        "4": {
            "sn": "00853",
            "brief": "不必翻译"
        },
        "5": {
            "sn": "03103",
            "brief": "约巴"
        },
        "6": {
            "sn": "00853",
            "brief": "不必翻译"
        },
        "7": {
            "sn": "06644",
            "brief": "洗比雅"
        },
        "8": {
            "sn": "00853",
            "brief": "不必翻译"
        },
        "9": {
            "sn": "04331",
            "brief": "米沙"
        },
        "10": {
            "sn": "00853",
            "brief": "不必翻译"
        },
        "11": {
            "sn": "04445",
            "brief": "玛拉干"
        },
        "0": {
            "sn": "03205",
            "brief": "生出、出生"
        },
        "literal": "他从他的妻子贺得生了约巴、和洗比雅、和米沙、和玛拉干、"
    },
    "2": {
        "literal": "比拉的子孙：亚达珥、和基拉、和亚比忽、",
        "0": {
            "sn": "01961",
            "brief": "是、成为、临到"
        },
        "1": {
            "sn": "01121",
            "brief": "儿子、孙子、后裔、成员"
        },
        "2": {
            "sn": "01106",
            "brief": "比拉"
        },
        "3": {
            "sn": "00146",
            "brief": "亚达珥"
        },
        "4": {
            "sn": "01617",
            "brief": "基拉"
        },
        "5": {
            "sn": "00031",
            "brief": "亚比忽"
        }
    },
    "4": {
        "literal": "和基拉、和示孚汛、和户兰。",
        "0": {
            "sn": "01617",
            "brief": "基拉"
        },
        "1": {
            "sn": "08197",
            "brief": "示孚汛"
        },
        "2": {
            "sn": "02361",
            "brief": "户兰"
        }
    },
    "6": {
        "literal": "乃幔、和亚希亚、和基拉，他掳走他们，他生了乌撒、和亚希忽。",
        "0": {
            "sn": "05283",
            "brief": "乃缦"
        },
        "1": {
            "sn": "00281",
            "brief": "亚希亚"
        },
        "2": {
            "sn": "01617",
            "brief": "基拉"
        },
        "3": {
            "sn": "01931",
            "brief": "他"
        },
        "5": {
            "sn": "03205",
            "brief": "生出、出生"
        },
        "6": {
            "sn": "00853",
            "brief": "不必翻译"
        },
        "7": {
            "sn": "05798",
            "brief": "乌撒"
        },
        "8": {
            "sn": "00853",
            "brief": "不必翻译"
        },
        "9": {
            "sn": "00284",
            "brief": "亚希忽"
        },
        "4": {
            "sn": "01540",
            "brief": "显露、揭开、移除、迁移"
        }
    },
    "35": {
        "13": {
            "sn": "03205",
            "brief": "生出、出生"
        },
        "1": {
            "sn": "03205",
            "brief": "生出、出生"
        },
        "literal": "亚哈斯生耶何阿达；耶何阿达生亚拉篾、和亚斯玛威、和心利；心利生摩撒；",
        "0": {
            "sn": "00271",
            "brief": "亚哈斯"
        },
        "2": {
            "sn": "00853",
            "brief": "不必翻译"
        },
        "3": {
            "sn": "03085",
            "brief": "耶何阿达"
        },
        "4": {
            "sn": "03085",
            "brief": "耶何阿达"
        },
        "6": {
            "sn": "00853",
            "brief": "不必翻译"
        },
        "7": {
            "sn": "05964",
            "brief": "亚拉篾"
        },
        "8": {
            "sn": "00853",
            "brief": "不必翻译"
        },
        "9": {
            "sn": "05820",
            "brief": "亚斯玛威"
        },
        "10": {
            "sn": "00853",
            "brief": "不必翻译"
        },
        "11": {
            "sn": "02174",
            "brief": "心利"
        },
        "12": {
            "sn": "02174",
            "brief": "心利"
        },
        "14": {
            "sn": "00853",
            "brief": "不必翻译"
        },
        "15": {
            "sn": "04162",
            "brief": "摩撒"
        },
        "5": {
            "sn": "03205",
            "brief": "生出、出生"
        }
    },
    "39": {
        "8": {
            "sn": "07235",
            "brief": "多、变多"
        },
        "literal": "乌兰的儿子都是大能的勇士，是弓箭手，有许多的子孙，(共)一百五十名，这些全都是便雅悯人。",
        "0": {
            "sn": "01961",
            "brief": "是、成为、临到"
        },
        "1": {
            "sn": "01121",
            "brief": "儿子、孙子、后裔、成员"
        },
        "2": {
            "sn": "00198",
            "brief": "乌兰"
        },
        "3": {
            "sn": "00376",
            "brief": "各人、人、男人、丈夫"
        },
        "4": {
            "sn": "01368",
            "brief": "形容词：强壮的、有力的；名词：勇士"
        },
        "5": {
            "sn": "02428",
            "brief": "军队、力量、财富、能力"
        },
        "6": {
            "sn": "01869",
            "brief": "踩踏、行进、引导、弯曲"
        },
        "7": {
            "sn": "07198",
            "brief": "弓"
        },
        "9": {
            "sn": "01121",
            "brief": "儿子、孙子、后裔、成员"
        },
        "10": {
            "sn": "01121",
            "brief": "儿子、孙子、后裔、成员"
        },
        "11": {
            "sn": "01121",
            "brief": "儿子、孙子、后裔、成员"
        },
        "12": {
            "sn": "03967",
            "brief": "数目的「一百」"
        },
        "13": {
            "sn": "02572",
            "brief": "数目的「五十」"
        },
        "14": {
            "sn": "03605",
            "brief": "全部、整个、任何事物"
        },
        "15": {
            "sn": "00428",
            "brief": "这些"
        },
        "16": {
            "sn": "01121",
            "brief": "儿子、孙子、后裔、成员"
        },
        "17": {
            "sn": "01144",
            "brief": "便雅悯"
        },
        "18": {
            "sn": "09015",
            "brief": "开的意思"
        }
    },
    "10": {
        "1": {
            "sn": "03205",
            "brief": "生出、出生"
        },
        "0": {
            "sn": "02366",
            "brief": "户伸"
        },
        "2": {
            "sn": "00853",
            "brief": "不必翻译"
        },
        "3": {
            "sn": "00036",
            "brief": "亚比突"
        },
        "4": {
            "sn": "00853",
            "brief": "不必翻译"
        },
        "5": {
            "sn": "00508",
            "brief": "以利巴力"
        },
        "literal": "而从户伸他生了亚比突和以利巴力。"
    },
    "36": {
        "literal": "摩撒生比尼亚；他(指比尼亚)的儿子是拉法；他(指拉法)的儿子是以利亚萨；他(指以利亚萨)的儿子是亚悉。",
        "0": {
            "sn": "04162",
            "brief": "摩撒"
        },
        "1": {
            "sn": "03205",
            "brief": "生出、出生"
        },
        "2": {
            "sn": "00853",
            "brief": "不必翻译"
        },
        "3": {
            "sn": "01150",
            "brief": "比尼亚"
        },
        "4": {
            "sn": "07498",
            "brief": "拉法"
        },
        "5": {
            "sn": "01121",
            "brief": "儿子、孙子、后裔、成员"
        },
        "6": {
            "sn": "00501",
            "brief": "以利亚萨"
        },
        "7": {
            "sn": "01121",
            "brief": "儿子、孙子、后裔、成员"
        },
        "8": {
            "sn": "00682",
            "brief": "亚悉"
        },
        "9": {
            "sn": "01121",
            "brief": "儿子、孙子、后裔、成员"
        }
    },
    "1": {
        "0": {
            "sn": "05119",
            "brief": "挪哈"
        },
        "literal": "四子挪哈，和五子拉法。",
        "1": {
            "sn": "07243",
            "brief": "序数的「第四」"
        },
        "2": {
            "sn": "07498",
            "brief": "拉法"
        },
        "3": {
            "sn": "02549",
            "brief": "序数的「第五」"
        },
        "4": {
            "sn": "09014",
            "brief": "关闭的意思"
        }
    },
    "34": {
        "literal": "弥迦的儿子是毗敦、和米勒、和他利亚、和亚哈斯；",
        "0": {
            "sn": "01121",
            "brief": "儿子、孙子、后裔、成员"
        },
        "1": {
            "sn": "04318",
            "brief": "弥迦"
        },
        "2": {
            "sn": "06377",
            "brief": "毗敦"
        },
        "3": {
            "sn": "04429",
            "brief": "米勒"
        },
        "4": {
            "sn": "08390",
            "brief": "他利亚"
        },
        "5": {
            "sn": "00271",
            "brief": "亚哈斯"
        }
    },
    "12": {
        "literal": "和比利亚，和示玛，他们是亚雅仑居民家族的族长，他们驱逐了迦特的居民。",
        "0": {
            "sn": "01283",
            "brief": "比利亚"
        },
        "1": {
            "sn": "08087",
            "brief": "示玛"
        },
        "2": {
            "sn": "01992",
            "brief": "他们"
        },
        "3": {
            "sn": "07218",
            "brief": "头、起头、山顶、领袖"
        },
        "4": {
            "sn": "00001",
            "brief": "父亲、祖先"
        },
        "5": {
            "sn": "03427",
            "brief": "居住、坐、停留"
        },
        "6": {
            "sn": "00357",
            "brief": "亚雅仑"
        },
        "7": {
            "sn": "01992",
            "brief": "他们、它们"
        },
        "9": {
            "sn": "00853",
            "brief": "不必翻译"
        },
        "10": {
            "sn": "03427",
            "brief": "居住、坐、停留"
        },
        "11": {
            "sn": "01661",
            "brief": "迦特"
        },
        "8": {
            "sn": "01272",
            "brief": "穿越、逃跑、赶快"
        }
    },
    "13": {
        "literal": "而亚希约、沙煞、和耶利末、",
        "0": {
            "sn": "00283",
            "brief": "亚希约"
        },
        "1": {
            "sn": "08349",
            "brief": "沙煞"
        },
        "2": {
            "sn": "03406",
            "brief": "耶利末"
        }
    },
    "14": {
        "literal": "和西巴第雅、和亚拉得、和亚得、",
        "0": {
            "sn": "02069",
            "brief": "西巴第雅"
        },
        "1": {
            "sn": "06166",
            "brief": "亚拉得"
        },
        "2": {
            "sn": "05738",
            "brief": "亚得"
        }
    },
    "15": {
        "literal": "和米迦勒、和伊施巴、和约哈(都)是比利亚的儿子。",
        "0": {
            "sn": "04317",
            "brief": "米迦勒"
        },
        "1": {
            "sn": "03472",
            "brief": "伊施巴"
        },
        "2": {
            "sn": "03109",
            "brief": "约哈"
        },
        "3": {
            "sn": "01121",
            "brief": "儿子、孙子、后裔、成员"
        },
        "4": {
            "sn": "01283",
            "brief": "比利亚"
        }
    },
    "17": {
        "literal": "和伊施米莱、和伊斯利亚、和约巴(都)是以利巴力的儿子。",
        "0": {
            "sn": "03461",
            "brief": "伊施米莱"
        },
        "1": {
            "sn": "03152",
            "brief": "伊斯利亚"
        },
        "2": {
            "sn": "03103",
            "brief": "约巴"
        },
        "3": {
            "sn": "01121",
            "brief": "儿子、孙子、后裔、成员"
        },
        "4": {
            "sn": "00508",
            "brief": "以利巴力"
        }
    },
    "18": {
        "literal": "而雅金、和细基利、和撒底、",
        "0": {
            "sn": "03356",
            "brief": "雅金"
        },
        "1": {
            "sn": "02147",
            "brief": "细基利"
        },
        "2": {
            "sn": "02067",
            "brief": "撒底"
        }
    },
    "21": {
        "literal": "而伊施班、和希伯、和以利业、",
        "0": {
            "sn": "03473",
            "brief": "伊施班"
        },
        "1": {
            "sn": "05677",
            "brief": "希伯"
        },
        "2": {
            "sn": "00447",
            "brief": "以利业"
        }
    },
    "24": {
        "0": {
            "sn": "03301",
            "brief": "伊弗底雅"
        },
        "1": {
            "sn": "06439",
            "brief": "毗努伊勒"
        },
        "2": {
            "sn": "01121",
            "brief": "儿子、孙子、后裔、成员"
        },
        "3": {
            "sn": "08349",
            "brief": "沙煞"
        },
        "literal": "和伊弗底雅、和毗努伊勒(都)是沙煞的儿子。"
    },
    "25": {
        "literal": "而珊示莱、和示哈利、和亚他利雅、",
        "0": {
            "sn": "08125",
            "brief": "珊示莱"
        },
        "1": {
            "sn": "07841",
            "brief": "示哈利"
        },
        "2": {
            "sn": "06271",
            "brief": "亚他利雅"
        }
    },
    "23": {
        "literal": "和哈拿尼雅、和以拦、和安陀提雅、",
        "0": {
            "sn": "02608",
            "brief": "哈拿尼雅"
        },
        "1": {
            "sn": "05867",
            "brief": "以拦"
        },
        "2": {
            "sn": "06070",
            "brief": "安陀提雅"
        }
    },
    "19": {
        "literal": "和以利乃、和洗勒太、和以利业、",
        "0": {
            "sn": "00462",
            "brief": "以利乃"
        },
        "1": {
            "sn": "06769",
            "brief": "洗勒太"
        },
        "2": {
            "sn": "00447",
            "brief": "以利业"
        }
    },
    "37": {
        "literal": "亚悉有六个儿子，这些是他们的名字：亚斯利干、波基路、和以实玛利、和示亚利雅、和俄巴底亚、和哈难。这些全都是亚悉的儿子。",
        "0": {
            "sn": "00682",
            "brief": "亚悉"
        },
        "1": {
            "sn": "08337",
            "brief": "数目的「六」"
        },
        "2": {
            "sn": "01121",
            "brief": "儿子、孙子、后裔、成员"
        },
        "3": {
            "sn": "00428",
            "brief": "这些"
        },
        "4": {
            "sn": "08034",
            "brief": "名字"
        },
        "5": {
            "sn": "05840",
            "brief": "亚斯利干"
        },
        "6": {
            "sn": "01074",
            "brief": "波基路"
        },
        "7": {
            "sn": "03458",
            "brief": "以实玛利"
        },
        "8": {
            "sn": "08187",
            "brief": "示亚利雅"
        },
        "9": {
            "sn": "05662",
            "brief": "俄巴底亚"
        },
        "10": {
            "sn": "02605",
            "brief": "哈难"
        },
        "11": {
            "sn": "03605",
            "brief": "全部、整个、各"
        },
        "12": {
            "sn": "00428",
            "brief": "这些"
        },
        "13": {
            "sn": "01121",
            "brief": "儿子、孙子、后裔、成员"
        },
        "14": {
            "sn": "00682",
            "brief": "亚悉"
        }
    }
}