{
    "15": {
        "7": {
            "sn": "04302",
            "brief": "预言"
        },
        "1": {
            "sn": "00080",
            "brief": "弟兄、兄弟"
        },
        "0": {
            "sn": "00435",
            "brief": "丈夫、男人、人"
        },
        "2": {
            "sn": "01163",
            "brief": "应该、必须"
        },
        "3": {
            "sn": "04137",
            "brief": "实现、充满"
        },
        "5": {
            "sn": "01124",
            "brief": "书、圣经"
        },
        "9": {
            "sn": "04151",
            "brief": "灵"
        },
        "12": {
            "sn": "01223",
            "brief": "后接所有格时意思是「通过、藉着」"
        },
        "13": {
            "sn": "04750",
            "brief": "口"
        },
        "14": {
            "sn": "01138",
            "brief": "专有名词，人名：大卫"
        },
        "15": {
            "sn": "04012",
            "brief": "后接所有格时意思是「关于」"
        },
        "16": {
            "sn": "02455",
            "brief": "专有名词，人名：犹大"
        },
        "18": {
            "sn": "01096",
            "brief": "发生、成为"
        },
        "19": {
            "sn": "03595",
            "brief": "领导者、向导"
        },
        "21": {
            "sn": "04815",
            "brief": "逮捕、抓"
        },
        "22": {
            "sn": "02424",
            "brief": "专有名词，人名：耶稣"
        },
        "6": {
            "sn": "03739",
            "brief": "带出关系子句修饰先行词"
        },
        "4": {
            "sn": "03588",
            "brief": "视情况翻译，有时可译成「这个」、「那个」等"
        },
        "8": {
            "sn": "03588",
            "brief": "视情况翻译，有时可译成「这个」、「那个」等"
        },
        "10": {
            "sn": "03588",
            "brief": "视情况翻译，有时可译成「这个」、「那个」等"
        },
        "11": {
            "sn": "00040",
            "brief": "圣洁的、圣的"
        },
        "17": {
            "sn": "03588",
            "brief": "视情况翻译，有时可译成「这个」、「那个」等"
        },
        "20": {
            "sn": "03588",
            "brief": "视情况翻译，有时可译成「这个」、「那个」等"
        }
    },
    "2": {
        "9": {
            "sn": "01722",
            "brief": "后接间接受格，意思是「藉着、在...里面、因为」"
        },
        "1": {
            "sn": "02532",
            "brief": "甚至、也、并且、然后、和"
        },
        "2": {
            "sn": "03936",
            "brief": "不及物时意思是「显现、站在一旁」"
        },
        "3": {
            "sn": "01438",
            "brief": "自己"
        },
        "4": {
            "sn": "02198",
            "brief": "活着"
        },
        "5": {
            "sn": "03326",
            "brief": "后接所有格时意思是「与....一起」"
        },
        "7": {
            "sn": "03958",
            "brief": "承受痛苦、经验"
        },
        "8": {
            "sn": "00846",
            "brief": "他"
        },
        "10": {
            "sn": "04183",
            "brief": "许多的"
        },
        "11": {
            "sn": "05039",
            "brief": "证据"
        },
        "0": {
            "sn": "03739",
            "brief": "带出关系子句修饰先行词"
        },
        "6": {
            "sn": "03588",
            "brief": "视情况翻译，有时可译成「这个」、「那个」等"
        },
        "13": {
            "sn": "02250",
            "brief": "日子"
        },
        "14": {
            "sn": "05062",
            "brief": "四十"
        },
        "15": {
            "sn": "03700",
            "brief": "出现、被看见"
        },
        "16": {
            "sn": "00846",
            "brief": "他"
        },
        "17": {
            "sn": "02532",
            "brief": "和、且、也"
        },
        "18": {
            "sn": "03004",
            "brief": "说"
        },
        "20": {
            "sn": "04012",
            "brief": "后接所有格时意思是「关于」"
        },
        "22": {
            "sn": "00932",
            "brief": "国家"
        },
        "24": {
            "sn": "02316",
            "brief": "上帝"
        },
        "19": {
            "sn": "03588",
            "brief": "视情况翻译，有时可译成「这个」、「那个」等"
        },
        "21": {
            "sn": "03588",
            "brief": "视情况翻译，有时可译成「这个」、「那个」等"
        },
        "23": {
            "sn": "03588",
            "brief": "视情况翻译，有时可译成「这个」、「那个」等"
        },
        "12": {
            "sn": "01223",
            "brief": "后接所有格时意思是「在...期间、通过」"
        }
    },
    "4": {
        "7": {
            "sn": "01722",
            "brief": "后接间接受格，意思是「藉着、在...里面、因为」"
        },
        "1": {
            "sn": "02491",
            "brief": "专有名词，人名：约翰"
        },
        "2": {
            "sn": "03303",
            "brief": "不必翻译，表示对比"
        },
        "3": {
            "sn": "00907",
            "brief": "施洗、浸"
        },
        "4": {
            "sn": "05204",
            "brief": "水"
        },
        "5": {
            "sn": "04771",
            "brief": "你"
        },
        "6": {
            "sn": "01161",
            "brief": "然后、但是、而"
        },
        "8": {
            "sn": "04151",
            "brief": "灵"
        },
        "9": {
            "sn": "00907",
            "brief": "施洗、浸"
        },
        "11": {
            "sn": "03756",
            "brief": "否定副词"
        },
        "13": {
            "sn": "04183",
            "brief": "许多的"
        },
        "14": {
            "sn": "03778",
            "brief": "这个"
        },
        "15": {
            "sn": "02250",
            "brief": "日子"
        },
        "0": {
            "sn": "03754",
            "brief": "因为、不必翻译带出子句"
        },
        "12": {
            "sn": "03326",
            "brief": "后接直接受格时意思是「在...之后」"
        },
        "10": {
            "sn": "00040",
            "brief": "圣洁的、圣的"
        }
    },
    "6": {
        "18": {
            "sn": "01722",
            "brief": "后接间接受格，意思是「藉着、在...里面、因为」"
        },
        "0": {
            "sn": "03004",
            "brief": "说"
        },
        "1": {
            "sn": "00000",
            "brief": ""
        },
        "2": {
            "sn": "00000",
            "brief": ""
        },
        "3": {
            "sn": "01161",
            "brief": "然后、但是、而"
        },
        "4": {
            "sn": "00000",
            "brief": ""
        },
        "5": {
            "sn": "04314",
            "brief": "后接直接受格时意思是「对、去到」，表达移动或面对的方向"
        },
        "6": {
            "sn": "00846",
            "brief": "他"
        },
        "7": {
            "sn": "03756",
            "brief": "否定副词"
        },
        "8": {
            "sn": "04771",
            "brief": "你"
        },
        "9": {
            "sn": "01510",
            "brief": "是、在、有"
        },
        "10": {
            "sn": "01097",
            "brief": "知道、认识"
        },
        "11": {
            "sn": "05550",
            "brief": "时刻、时间"
        },
        "12": {
            "sn": "02228",
            "brief": "或、比"
        },
        "13": {
            "sn": "02540",
            "brief": "时刻、时间"
        },
        "16": {
            "sn": "03962",
            "brief": "父"
        },
        "17": {
            "sn": "05087",
            "brief": "设定、安放"
        },
        "20": {
            "sn": "02398",
            "brief": "自己的"
        },
        "21": {
            "sn": "01849",
            "brief": "权柄、权威"
        },
        "14": {
            "sn": "03739",
            "brief": "带出关系子句修饰先行词"
        },
        "15": {
            "sn": "03588",
            "brief": "视情况翻译，有时可译成「这个」、「那个」等"
        },
        "19": {
            "sn": "03588",
            "brief": "视情况翻译，有时可译成「这个」、「那个」等"
        }
    },
    "23": {
        "13": {
            "sn": "01417",
            "brief": "两个"
        },
        "0": {
            "sn": "02532",
            "brief": "然后、不必翻译"
        },
        "1": {
            "sn": "04336",
            "brief": "祷告"
        },
        "2": {
            "sn": "03004",
            "brief": "说"
        },
        "3": {
            "sn": "04771",
            "brief": "你"
        },
        "4": {
            "sn": "02962",
            "brief": "主"
        },
        "5": {
            "sn": "02589",
            "brief": "知道人心的"
        },
        "6": {
            "sn": "03956",
            "brief": "所有的、每一个"
        },
        "7": {
            "sn": "00322",
            "brief": "显明、指派"
        },
        "9": {
            "sn": "01586",
            "brief": "选出，关身时意思是「拣选」"
        },
        "10": {
            "sn": "01537",
            "brief": "后接所有格，意思是「出于、从」"
        },
        "11": {
            "sn": "03778",
            "brief": "这个"
        },
        "14": {
            "sn": "01520",
            "brief": "一个的"
        },
        "8": {
            "sn": "03739",
            "brief": "带出关系子句修饰先行词"
        },
        "12": {
            "sn": "03588",
            "brief": "视情况翻译，有时可译成「这个」、「那个」等"
        }
    },
    "14": {
        "23": {
            "sn": "00000",
            "brief": ""
        },
        "22": {
            "sn": "05616",
            "brief": "约有、正如"
        },
        "10": {
            "sn": "00080",
            "brief": "弟兄、兄弟"
        },
        "0": {
            "sn": "02532",
            "brief": "然后、且、和"
        },
        "3": {
            "sn": "02250",
            "brief": "日子"
        },
        "4": {
            "sn": "03778",
            "brief": "这个"
        },
        "6": {
            "sn": "04074",
            "brief": "专有名词，人名：彼得"
        },
        "8": {
            "sn": "03319",
            "brief": "中间的"
        },
        "11": {
            "sn": "03004",
            "brief": "说"
        },
        "12": {
            "sn": "01510",
            "brief": "在、是、有"
        },
        "13": {
            "sn": "05037",
            "brief": "且"
        },
        "14": {
            "sn": "03793",
            "brief": "群众"
        },
        "15": {
            "sn": "03686",
            "brief": "人们、名字"
        },
        "19": {
            "sn": "00000",
            "brief": ""
        },
        "20": {
            "sn": "05613",
            "brief": "约有、正如"
        },
        "21": {
            "sn": "00000",
            "brief": ""
        },
        "18": {
            "sn": "00846",
            "brief": "形容词时意思是「相同的」"
        },
        "2": {
            "sn": "03588",
            "brief": "视情况翻译，有时可译成「这个」、「那个」等"
        },
        "9": {
            "sn": "03588",
            "brief": "视情况翻译，有时可译成「这个」、「那个」等"
        },
        "24": {
            "sn": "01540",
            "brief": "一百"
        },
        "25": {
            "sn": "01501",
            "brief": "二十"
        },
        "5": {
            "sn": "00450",
            "brief": "站起来、使...起来"
        },
        "16": {
            "sn": "01909",
            "brief": "后接直接受格时意思是「在...上面」，表达移动或面对的方向"
        },
        "7": {
            "sn": "01722",
            "brief": "后接间接受格，意思是「在...中间、在...里面、藉着」"
        },
        "17": {
            "sn": "03588",
            "brief": "视情况翻译，有时可译成「这个」、「那个」等"
        },
        "1": {
            "sn": "01722",
            "brief": "后接间接受格，意思是「在...里面、藉着」"
        }
    },
    "7": {
        "11": {
            "sn": "01473",
            "brief": "我"
        },
        "0": {
            "sn": "00235",
            "brief": "但"
        },
        "1": {
            "sn": "02983",
            "brief": "领受、接受"
        },
        "2": {
            "sn": "01411",
            "brief": "能力"
        },
        "3": {
            "sn": "01904",
            "brief": "来临"
        },
        "6": {
            "sn": "04151",
            "brief": "灵"
        },
        "8": {
            "sn": "04771",
            "brief": "你"
        },
        "9": {
            "sn": "02532",
            "brief": "和、但、且、也"
        },
        "10": {
            "sn": "01510",
            "brief": "是、在、有"
        },
        "12": {
            "sn": "03144",
            "brief": "见证人"
        },
        "14": {
            "sn": "05037",
            "brief": "且"
        },
        "15": {
            "sn": "02414",
            "brief": "专有名词，地名：耶路撒冷"
        },
        "16": {
            "sn": "02532",
            "brief": "和、但、且、也"
        },
        "18": {
            "sn": "03956",
            "brief": "所有的、每一个"
        },
        "20": {
            "sn": "02449",
            "brief": "专有名词，地名：犹太"
        },
        "21": {
            "sn": "02532",
            "brief": "和、但、且、也"
        },
        "22": {
            "sn": "00000",
            "brief": ""
        },
        "23": {
            "sn": "04540",
            "brief": "专有名词，地名：撒马利亚"
        },
        "24": {
            "sn": "00000",
            "brief": ""
        },
        "25": {
            "sn": "04540",
            "brief": "专有名词，地名：撒马利亚"
        },
        "26": {
            "sn": "00000",
            "brief": ""
        },
        "27": {
            "sn": "02532",
            "brief": "并且、和、然后"
        },
        "29": {
            "sn": "02078",
            "brief": "最后的"
        },
        "31": {
            "sn": "01093",
            "brief": "地"
        },
        "19": {
            "sn": "03588",
            "brief": "视情况翻译，有时可译成「这个」、「那个」等"
        },
        "30": {
            "sn": "03588",
            "brief": "视情况翻译，有时可译成「这个」、「那个」等"
        },
        "7": {
            "sn": "01909",
            "brief": "后接直接受格时意思是「在...上面」"
        },
        "28": {
            "sn": "02193",
            "brief": "后接所有格时意思为「直到、当...时」"
        },
        "4": {
            "sn": "03588",
            "brief": "视情况翻译，有时可译成「这个」、「那个」等"
        },
        "13": {
            "sn": "01722",
            "brief": "后接间接受格，意思是「在...里面、藉着」"
        },
        "17": {
            "sn": "01722",
            "brief": "后接间接受格，意思是「在...里面、藉着」"
        },
        "5": {
            "sn": "00040",
            "brief": "圣洁的、圣的"
        }
    },
    "0": {
        "7": {
            "sn": "05599",
            "brief": "喔！"
        },
        "1": {
            "sn": "03303",
            "brief": "不必翻译，表示对比"
        },
        "2": {
            "sn": "04413",
            "brief": "之前、第一"
        },
        "3": {
            "sn": "03056",
            "brief": "言语、道"
        },
        "4": {
            "sn": "04160",
            "brief": "做，关身时意思是「用自己的资源做」、「为自己做」"
        },
        "5": {
            "sn": "04012",
            "brief": "后接所有格时意思是「关于」"
        },
        "6": {
            "sn": "03956",
            "brief": "所有的、每一个"
        },
        "8": {
            "sn": "02321",
            "brief": "专有名词，人名：提阿非罗"
        },
        "10": {
            "sn": "00757",
            "brief": "成第一，关身时意思是「开始」"
        },
        "11": {
            "sn": "00000",
            "brief": ""
        },
        "12": {
            "sn": "00000",
            "brief": ""
        },
        "14": {
            "sn": "00000",
            "brief": ""
        },
        "15": {
            "sn": "02424",
            "brief": "专有名词，人名：耶稣"
        },
        "16": {
            "sn": "04160",
            "brief": "做"
        },
        "17": {
            "sn": "05037",
            "brief": "且"
        },
        "18": {
            "sn": "02532",
            "brief": "和、但、且、也"
        },
        "19": {
            "sn": "01321",
            "brief": "教导"
        },
        "9": {
            "sn": "03739",
            "brief": "带出关系子句修饰先行词"
        },
        "0": {
            "sn": "03588",
            "brief": "视情况翻译，有时可译成「这个」、「那个」等"
        },
        "13": {
            "sn": "03588",
            "brief": "视情况翻译，有时可译成「这个」、「那个」等"
        }
    },
    "1": {
        "0": {
            "sn": "00891",
            "brief": "后接所有格，意思是「直到」"
        },
        "2": {
            "sn": "02250",
            "brief": "日子"
        },
        "3": {
            "sn": "01781",
            "brief": "命令"
        },
        "5": {
            "sn": "00652",
            "brief": "使徒"
        },
        "6": {
            "sn": "01223",
            "brief": "后接所有格时意思是「通过、藉着」"
        },
        "7": {
            "sn": "04151",
            "brief": "灵"
        },
        "10": {
            "sn": "01586",
            "brief": "选出，关身时意思是「拣选」"
        },
        "11": {
            "sn": "00353",
            "brief": "使升高，被动时意思是「被接走」"
        },
        "1": {
            "sn": "03739",
            "brief": "带出关系子句修饰先行词"
        },
        "9": {
            "sn": "03739",
            "brief": "带出关系子句修饰先行词"
        },
        "4": {
            "sn": "03588",
            "brief": "视情况翻译，有时可译成「这个」、「那个」等"
        },
        "8": {
            "sn": "00040",
            "brief": "圣洁的、圣的"
        }
    },
    "5": {
        "6": {
            "sn": "03004",
            "brief": "说"
        },
        "1": {
            "sn": "03303",
            "brief": "不必翻译"
        },
        "2": {
            "sn": "03767",
            "brief": "这样、所以"
        },
        "3": {
            "sn": "04905",
            "brief": "聚集、在一起"
        },
        "4": {
            "sn": "02065",
            "brief": "问、求"
        },
        "5": {
            "sn": "00846",
            "brief": "他"
        },
        "7": {
            "sn": "02962",
            "brief": "主"
        },
        "8": {
            "sn": "01487",
            "brief": "是否、假若"
        },
        "11": {
            "sn": "05550",
            "brief": "时间"
        },
        "12": {
            "sn": "03778",
            "brief": "这个"
        },
        "13": {
            "sn": "00600",
            "brief": "重建、医好"
        },
        "15": {
            "sn": "00932",
            "brief": "国家"
        },
        "17": {
            "sn": "02474",
            "brief": "专有名词，国名、地名、人名：以色列"
        },
        "10": {
            "sn": "03588",
            "brief": "视情况翻译，有时可译成「这个」、「那个」等"
        },
        "14": {
            "sn": "03588",
            "brief": "视情况翻译，有时可译成「这个」、「那个」等"
        },
        "16": {
            "sn": "03588",
            "brief": "视情况翻译，有时可译成「这个」、「那个」等"
        },
        "0": {
            "sn": "03588",
            "brief": "视情况翻译，有时可译成「这个」、「那个」等"
        },
        "9": {
            "sn": "01722",
            "brief": "后接间接受格，意思是「在...里面、藉着」"
        }
    },
    "3": {
        "0": {
            "sn": "02532",
            "brief": "然后、不必翻译"
        },
        "1": {
            "sn": "04871",
            "brief": "聚集"
        },
        "2": {
            "sn": "03853",
            "brief": "命令"
        },
        "3": {
            "sn": "00846",
            "brief": "他"
        },
        "4": {
            "sn": "00575",
            "brief": "后接所有格，意思是「从」"
        },
        "5": {
            "sn": "02414",
            "brief": "专有名词，地名：耶路撒冷"
        },
        "6": {
            "sn": "03361",
            "brief": "否定副词"
        },
        "7": {
            "sn": "05563",
            "brief": "离开"
        },
        "8": {
            "sn": "00235",
            "brief": "但"
        },
        "9": {
            "sn": "04037",
            "brief": "等候"
        },
        "11": {
            "sn": "01860",
            "brief": "应许、承诺"
        },
        "13": {
            "sn": "03962",
            "brief": "父"
        },
        "15": {
            "sn": "00191",
            "brief": "听见"
        },
        "16": {
            "sn": "01473",
            "brief": "我"
        },
        "14": {
            "sn": "03739",
            "brief": "带出关系子句修饰先行词"
        },
        "10": {
            "sn": "03588",
            "brief": "视情况翻译，有时可译成「这个」、「那个」等"
        },
        "12": {
            "sn": "03588",
            "brief": "视情况翻译，有时可译成「这个」、「那个」等"
        }
    },
    "9": {
        "9": {
            "sn": "02532",
            "brief": "甚至、也、并且、然后、和"
        },
        "0": {
            "sn": "02532",
            "brief": "然后、并且、和"
        },
        "1": {
            "sn": "05613",
            "brief": "如此、正当、如同、好像"
        },
        "2": {
            "sn": "00816",
            "brief": "凝视"
        },
        "4": {
            "sn": "01519",
            "brief": "后接直接受格，意思是「朝向、进入 」"
        },
        "6": {
            "sn": "03772",
            "brief": "天"
        },
        "7": {
            "sn": "04198",
            "brief": "去、前进、旅行"
        },
        "8": {
            "sn": "00846",
            "brief": "他"
        },
        "10": {
            "sn": "02400",
            "brief": "看哪！、注意！"
        },
        "11": {
            "sn": "00435",
            "brief": "人、丈夫、男人"
        },
        "12": {
            "sn": "01417",
            "brief": "两个"
        },
        "13": {
            "sn": "00000",
            "brief": ""
        },
        "5": {
            "sn": "03588",
            "brief": "视情况翻译，有时可译成「这个」、「那个」等"
        },
        "14": {
            "sn": "03936",
            "brief": "显出自己，不及物时意思是「显现、站在一旁」"
        },
        "15": {
            "sn": "00000",
            "brief": ""
        },
        "16": {
            "sn": "03936",
            "brief": "显出自己，不及物时意思是「显现、站在一旁」"
        },
        "17": {
            "sn": "00000",
            "brief": ""
        },
        "18": {
            "sn": "00846",
            "brief": "他"
        },
        "20": {
            "sn": "02066",
            "brief": "衣服"
        },
        "21": {
            "sn": "03022",
            "brief": "白色的、耀眼的"
        },
        "3": {
            "sn": "01510",
            "brief": "是、有"
        },
        "19": {
            "sn": "01722",
            "brief": "后接间接受格，意思是「在...里面、藉着」"
        }
    },
    "8": {
        "0": {
            "sn": "02532",
            "brief": "然后、不必翻译"
        },
        "1": {
            "sn": "03778",
            "brief": "这"
        },
        "2": {
            "sn": "03004",
            "brief": "说"
        },
        "3": {
            "sn": "00991",
            "brief": "看、看见"
        },
        "4": {
            "sn": "00846",
            "brief": "他"
        },
        "5": {
            "sn": "01869",
            "brief": "举高、提高"
        },
        "6": {
            "sn": "02532",
            "brief": "然后、不必翻译"
        },
        "7": {
            "sn": "03507",
            "brief": "云"
        },
        "8": {
            "sn": "05274",
            "brief": "接走"
        },
        "9": {
            "sn": "00846",
            "brief": "他"
        },
        "10": {
            "sn": "00575",
            "brief": "后接所有格，意思是「从」"
        },
        "12": {
            "sn": "03788",
            "brief": "眼睛"
        },
        "13": {
            "sn": "00846",
            "brief": "他"
        },
        "11": {
            "sn": "03588",
            "brief": "视情况翻译，有时可译成「这个」、「那个」等"
        }
    },
    "10": {
        "1": {
            "sn": "02532",
            "brief": "甚至、也、并且、然后、和"
        },
        "2": {
            "sn": "03004",
            "brief": "说"
        },
        "3": {
            "sn": "00435",
            "brief": "人、丈夫、男人"
        },
        "4": {
            "sn": "01057",
            "brief": "加利利的"
        },
        "5": {
            "sn": "05101",
            "brief": "为什么"
        },
        "6": {
            "sn": "02476",
            "brief": "站立"
        },
        "7": {
            "sn": "00000",
            "brief": ""
        },
        "8": {
            "sn": "00991",
            "brief": "看"
        },
        "9": {
            "sn": "00000",
            "brief": ""
        },
        "10": {
            "sn": "01689",
            "brief": "凝视"
        },
        "11": {
            "sn": "00000",
            "brief": ""
        },
        "12": {
            "sn": "01519",
            "brief": "后接直接受格，意思是「朝向、进入 」"
        },
        "14": {
            "sn": "03772",
            "brief": "天"
        },
        "15": {
            "sn": "03778",
            "brief": "这个"
        },
        "17": {
            "sn": "02424",
            "brief": "专有名词，人名：耶稣"
        },
        "19": {
            "sn": "00353",
            "brief": "使升高，被动时意思是「被接走」"
        },
        "20": {
            "sn": "00575",
            "brief": "后接所有格，意思是「从」"
        },
        "21": {
            "sn": "04771",
            "brief": "你"
        },
        "22": {
            "sn": "01519",
            "brief": "后接直接受格，意思是「进入、朝向 」"
        },
        "24": {
            "sn": "03772",
            "brief": "天"
        },
        "25": {
            "sn": "03779",
            "brief": "如此、这样地"
        },
        "26": {
            "sn": "02064",
            "brief": "去"
        },
        "28": {
            "sn": "05158",
            "brief": "方法、方向"
        },
        "29": {
            "sn": "02300",
            "brief": "看"
        },
        "30": {
            "sn": "00846",
            "brief": "他"
        },
        "31": {
            "sn": "04198",
            "brief": "去、前进、旅行"
        },
        "32": {
            "sn": "01519",
            "brief": "后接直接受格，意思是「朝向、进入 」"
        },
        "34": {
            "sn": "03772",
            "brief": "天"
        },
        "0": {
            "sn": "03739",
            "brief": "带出关系子句修饰先行词"
        },
        "27": {
            "sn": "03739",
            "brief": "带出关系子句修饰先行词"
        },
        "13": {
            "sn": "03588",
            "brief": "视情况翻译，有时可译成「这个」、「那个」等"
        },
        "16": {
            "sn": "03588",
            "brief": "视情况翻译，有时可译成「这个」、「那个」等"
        },
        "18": {
            "sn": "03588",
            "brief": "视情况翻译，有时可译成「这个」、「那个」等"
        },
        "23": {
            "sn": "03588",
            "brief": "视情况翻译，有时可译成「这个」、「那个」等"
        },
        "33": {
            "sn": "03588",
            "brief": "视情况翻译，有时可译成「这个」、「那个」等"
        }
    },
    "12": {
        "27": {
            "sn": "02532",
            "brief": "和、且"
        },
        "28": {
            "sn": "04613",
            "brief": "专有名词，人名：西门"
        },
        "0": {
            "sn": "02532",
            "brief": "然后、不必翻译"
        },
        "2": {
            "sn": "01525",
            "brief": "进入"
        },
        "3": {
            "sn": "01519",
            "brief": "后接直接受格，意思是「朝向、进入 」"
        },
        "5": {
            "sn": "05253",
            "brief": "屋子上层"
        },
        "6": {
            "sn": "00305",
            "brief": "登高、上去"
        },
        "7": {
            "sn": "03757",
            "brief": "为关系副词，意思是「那地」或不必翻译"
        },
        "9": {
            "sn": "02650",
            "brief": "停留、居住"
        },
        "11": {
            "sn": "05037",
            "brief": "且"
        },
        "12": {
            "sn": "04074",
            "brief": "专有名词，人名：彼得"
        },
        "13": {
            "sn": "02532",
            "brief": "和、且"
        },
        "14": {
            "sn": "02491",
            "brief": "专有名词，人名：约翰"
        },
        "15": {
            "sn": "02532",
            "brief": "和、且"
        },
        "16": {
            "sn": "02385",
            "brief": "专有名词，人名：雅各"
        },
        "17": {
            "sn": "02532",
            "brief": "和、且"
        },
        "18": {
            "sn": "00406",
            "brief": "专有名词，人名：安得烈"
        },
        "19": {
            "sn": "05376",
            "brief": "专有名词，人名：腓力"
        },
        "20": {
            "sn": "02532",
            "brief": "和、且"
        },
        "21": {
            "sn": "02381",
            "brief": "专有名词，人名：多马"
        },
        "22": {
            "sn": "00918",
            "brief": "专有名词，人名：巴多罗买"
        },
        "23": {
            "sn": "02532",
            "brief": "和、且"
        },
        "24": {
            "sn": "03156",
            "brief": "专有名词，人名：马太"
        },
        "25": {
            "sn": "02385",
            "brief": "专有名词，人名：雅各"
        },
        "26": {
            "sn": "00256",
            "brief": "专有名词，人名：亚勒腓"
        },
        "30": {
            "sn": "02207",
            "brief": "狂热份子、奋锐党"
        },
        "31": {
            "sn": "02532",
            "brief": "和、且"
        },
        "32": {
            "sn": "02455",
            "brief": "专有名词，人名：犹大"
        },
        "33": {
            "sn": "02385",
            "brief": "专有名词，人名：雅各"
        },
        "1": {
            "sn": "03753",
            "brief": "当...的时候"
        },
        "4": {
            "sn": "03588",
            "brief": "视情况翻译，有时可译成「这个」、「那个」等"
        },
        "10": {
            "sn": "03588",
            "brief": "视情况翻译，有时可译成「这个」、「那个」等"
        },
        "29": {
            "sn": "03588",
            "brief": "视情况翻译，有时可译成「这个」、「那个」等"
        },
        "8": {
            "sn": "01510",
            "brief": "是、有"
        }
    },
    "11": {
        "0": {
            "sn": "05119",
            "brief": "那时"
        },
        "1": {
            "sn": "05290",
            "brief": "转向、回来"
        },
        "2": {
            "sn": "01519",
            "brief": "后接直接受格，意思是「朝向、进入 」"
        },
        "3": {
            "sn": "02414",
            "brief": "专有名词，地名：耶路撒冷"
        },
        "4": {
            "sn": "00575",
            "brief": "后接所有格，意思是「从」"
        },
        "5": {
            "sn": "03735",
            "brief": "山、山丘"
        },
        "7": {
            "sn": "02564",
            "brief": "取名、叫"
        },
        "8": {
            "sn": "01638",
            "brief": "橄榄"
        },
        "10": {
            "sn": "01510",
            "brief": "是、在、有"
        },
        "11": {
            "sn": "01451",
            "brief": "靠近"
        },
        "12": {
            "sn": "02414",
            "brief": "专有名词，地名：耶路撒冷"
        },
        "13": {
            "sn": "04521",
            "brief": "安息日"
        },
        "14": {
            "sn": "02192",
            "brief": "有"
        },
        "15": {
            "sn": "03598",
            "brief": "道路、路程"
        },
        "9": {
            "sn": "03739",
            "brief": "带出关系子句修饰先行词"
        },
        "6": {
            "sn": "03588",
            "brief": "视情况翻译，有时可译成「这个」、「那个」等"
        }
    },
    "13": {
        "25": {
            "sn": "00080",
            "brief": "弟兄、兄弟"
        },
        "0": {
            "sn": "03778",
            "brief": "这个"
        },
        "1": {
            "sn": "03956",
            "brief": "所有的、每一个"
        },
        "3": {
            "sn": "04342",
            "brief": "专注、持续"
        },
        "4": {
            "sn": "03661",
            "brief": "同心地"
        },
        "6": {
            "sn": "04335",
            "brief": "祷告"
        },
        "8": {
            "sn": "01135",
            "brief": "女人、妻子"
        },
        "9": {
            "sn": "02532",
            "brief": "和、且"
        },
        "10": {
            "sn": "03137",
            "brief": "专有名词，人名：马利亚"
        },
        "12": {
            "sn": "03384",
            "brief": "母亲"
        },
        "13": {
            "sn": "00000",
            "brief": ""
        },
        "15": {
            "sn": "00000",
            "brief": ""
        },
        "17": {
            "sn": "00000",
            "brief": ""
        },
        "18": {
            "sn": "02424",
            "brief": "专有名词，人名：耶稣"
        },
        "19": {
            "sn": "02532",
            "brief": "和、且"
        },
        "20": {
            "sn": "00000",
            "brief": ""
        },
        "22": {
            "sn": "00000",
            "brief": ""
        },
        "23": {
            "sn": "00000",
            "brief": ""
        },
        "26": {
            "sn": "00846",
            "brief": "他"
        },
        "5": {
            "sn": "03588",
            "brief": "视情况翻译，有时可译成「这个」、「那个」等"
        },
        "11": {
            "sn": "03588",
            "brief": "视情况翻译，有时可译成「这个」、「那个」等"
        },
        "14": {
            "sn": "03588",
            "brief": "视情况翻译，有时可译成「这个」、「那个」等"
        },
        "16": {
            "sn": "03588",
            "brief": "视情况翻译，有时可译成「这个」、「那个」等"
        },
        "24": {
            "sn": "03588",
            "brief": "视情况翻译，有时可译成「这个」、「那个」等"
        },
        "7": {
            "sn": "04862",
            "brief": "后接间接受格，意思是「与...一起」"
        },
        "21": {
            "sn": "04862",
            "brief": "后接间接受格，意思是「与...一起」"
        },
        "2": {
            "sn": "01510",
            "brief": "是、有"
        }
    },
    "16": {
        "1": {
            "sn": "02674",
            "brief": "数在内"
        },
        "4": {
            "sn": "01473",
            "brief": "我"
        },
        "5": {
            "sn": "02532",
            "brief": "并且、然后"
        },
        "6": {
            "sn": "02975",
            "brief": "得到(并非靠自己)、抽签"
        },
        "8": {
            "sn": "02819",
            "brief": "(分发的)一份、签"
        },
        "10": {
            "sn": "01248",
            "brief": "服事、职分"
        },
        "11": {
            "sn": "03778",
            "brief": "这个"
        },
        "0": {
            "sn": "03754",
            "brief": "因为、不必翻译带出子句"
        },
        "3": {
            "sn": "01722",
            "brief": "后接间接受格，意思是「在...中间、在...里面、藉着」"
        },
        "7": {
            "sn": "03588",
            "brief": "视情况翻译，有时可译成「这个」、「那个」等"
        },
        "9": {
            "sn": "03588",
            "brief": "视情况翻译，有时可译成「这个」、「那个」等"
        },
        "2": {
            "sn": "01510",
            "brief": "是、有"
        }
    },
    "17": {
        "0": {
            "sn": "03778",
            "brief": "这个"
        },
        "1": {
            "sn": "03303",
            "brief": "不必翻译"
        },
        "2": {
            "sn": "03767",
            "brief": "这样、所以"
        },
        "3": {
            "sn": "02932",
            "brief": "获得、拥有、买"
        },
        "4": {
            "sn": "05564",
            "brief": "土地、地方"
        },
        "5": {
            "sn": "01537",
            "brief": "后接所有格，意思是「出于、从」"
        },
        "6": {
            "sn": "03408",
            "brief": "报酬、工资"
        },
        "8": {
            "sn": "00093",
            "brief": "罪行、邪恶"
        },
        "9": {
            "sn": "02532",
            "brief": "并且、然后"
        },
        "10": {
            "sn": "04248",
            "brief": "头下脚上的、倒栽葱的"
        },
        "11": {
            "sn": "01096",
            "brief": "发生、成为"
        },
        "12": {
            "sn": "02997",
            "brief": "撞毁、破裂"
        },
        "13": {
            "sn": "03319",
            "brief": "中间的"
        },
        "14": {
            "sn": "02532",
            "brief": "并且、然后"
        },
        "15": {
            "sn": "01632",
            "brief": "流出"
        },
        "16": {
            "sn": "03956",
            "brief": "所有的、每一个"
        },
        "18": {
            "sn": "04698",
            "brief": "肠子、内脏"
        },
        "19": {
            "sn": "00846",
            "brief": "他"
        },
        "17": {
            "sn": "03588",
            "brief": "视情况翻译，有时可译成「这个」、「那个」等"
        },
        "7": {
            "sn": "03588",
            "brief": "视情况翻译，有时可译成「这个」、「那个」等"
        }
    },
    "18": {
        "0": {
            "sn": "02532",
            "brief": "并且、然后、和"
        },
        "1": {
            "sn": "01110",
            "brief": "知道的、认识的"
        },
        "2": {
            "sn": "01096",
            "brief": "发生、成为"
        },
        "3": {
            "sn": "03956",
            "brief": "所有的、每一个"
        },
        "5": {
            "sn": "02730",
            "brief": "居住"
        },
        "6": {
            "sn": "02414",
            "brief": "专有名词，地名：耶路撒冷"
        },
        "7": {
            "sn": "05620",
            "brief": "因此"
        },
        "8": {
            "sn": "02564",
            "brief": "取名、叫"
        },
        "10": {
            "sn": "05564",
            "brief": "土地、地方、田"
        },
        "11": {
            "sn": "01565",
            "brief": "那个"
        },
        "13": {
            "sn": "00000",
            "brief": ""
        },
        "14": {
            "sn": "00000",
            "brief": ""
        },
        "15": {
            "sn": "02398",
            "brief": "自己的"
        },
        "16": {
            "sn": "00000",
            "brief": ""
        },
        "17": {
            "sn": "01258",
            "brief": "语言"
        },
        "18": {
            "sn": "00846",
            "brief": "他"
        },
        "19": {
            "sn": "00184",
            "brief": "亚革大马，亚兰文的意思是「血之田」"
        },
        "20": {
            "sn": "03778",
            "brief": "这个"
        },
        "21": {
            "sn": "01510",
            "brief": "是、在、有"
        },
        "22": {
            "sn": "05564",
            "brief": "土地、地方"
        },
        "23": {
            "sn": "00129",
            "brief": "血、死亡"
        },
        "4": {
            "sn": "03588",
            "brief": "视情况翻译，有时可译成「这个」、「那个」等"
        },
        "9": {
            "sn": "03588",
            "brief": "视情况翻译，有时可译成「这个」、「那个」等"
        },
        "12": {
            "sn": "03588",
            "brief": "视情况翻译，有时可译成「这个」、「那个」等"
        }
    },
    "21": {
        "1": {
            "sn": "00575",
            "brief": "后接所有格，意思是「从」"
        },
        "0": {
            "sn": "00757",
            "brief": "成第一，关身时意思是「开始」"
        },
        "3": {
            "sn": "00908",
            "brief": "洗礼"
        },
        "4": {
            "sn": "02491",
            "brief": "专有名词，人名：约翰"
        },
        "5": {
            "sn": "02193",
            "brief": "后接所有格，意思是「直到」"
        },
        "7": {
            "sn": "02250",
            "brief": "日子"
        },
        "9": {
            "sn": "00353",
            "brief": "使升高，被动时意思是「被接走」"
        },
        "10": {
            "sn": "00575",
            "brief": "后接所有格，意思是「从」"
        },
        "11": {
            "sn": "01473",
            "brief": "我"
        },
        "12": {
            "sn": "03144",
            "brief": "见证人"
        },
        "14": {
            "sn": "00386",
            "brief": "复活"
        },
        "15": {
            "sn": "00846",
            "brief": "他"
        },
        "17": {
            "sn": "01473",
            "brief": "我"
        },
        "18": {
            "sn": "01096",
            "brief": "发生、成为"
        },
        "19": {
            "sn": "01520",
            "brief": "一个的"
        },
        "20": {
            "sn": "03778",
            "brief": "这个"
        },
        "8": {
            "sn": "03739",
            "brief": "带出关系子句修饰先行词"
        },
        "6": {
            "sn": "03588",
            "brief": "视情况翻译，有时可译成「这个」、「那个」等"
        },
        "13": {
            "sn": "03588",
            "brief": "视情况翻译，有时可译成「这个」、「那个」等"
        },
        "16": {
            "sn": "04862",
            "brief": "后接间接受格，意思是「跟...一同」"
        },
        "2": {
            "sn": "03588",
            "brief": "视情况翻译，有时可译成「这个」、「那个」等"
        }
    },
    "19": {
        "0": {
            "sn": "01125",
            "brief": "写"
        },
        "1": {
            "sn": "01063",
            "brief": "因为"
        },
        "3": {
            "sn": "00976",
            "brief": "书、草纸、树皮"
        },
        "4": {
            "sn": "05568",
            "brief": "诗篇、圣歌"
        },
        "5": {
            "sn": "01096",
            "brief": "发生、成为"
        },
        "7": {
            "sn": "01886",
            "brief": "住处"
        },
        "8": {
            "sn": "00846",
            "brief": "他"
        },
        "9": {
            "sn": "02048",
            "brief": "荒废的"
        },
        "10": {
            "sn": "02532",
            "brief": "并且、然后、不必翻译"
        },
        "11": {
            "sn": "03361",
            "brief": "否定副词"
        },
        "14": {
            "sn": "02730",
            "brief": "居住"
        },
        "16": {
            "sn": "00846",
            "brief": "他"
        },
        "17": {
            "sn": "02532",
            "brief": "并且、然后、不必翻译"
        },
        "19": {
            "sn": "01984",
            "brief": "监督看顾的职位、看顾、监督"
        },
        "20": {
            "sn": "00846",
            "brief": "他"
        },
        "21": {
            "sn": "02983",
            "brief": "领受、接受"
        },
        "22": {
            "sn": "02087",
            "brief": "另外的"
        },
        "13": {
            "sn": "03588",
            "brief": "视情况翻译，有时可译成「这个」、「那个」等"
        },
        "18": {
            "sn": "03588",
            "brief": "视情况翻译，有时可译成「这个」、「那个」等"
        },
        "6": {
            "sn": "03588",
            "brief": "视情况翻译，有时可译成「这个」、「那个」等"
        },
        "12": {
            "sn": "01510",
            "brief": "是、有"
        },
        "2": {
            "sn": "01722",
            "brief": "后接间接受格，意思是「在...里面、藉着」"
        },
        "15": {
            "sn": "01722",
            "brief": "后接间接受格，意思是「在...里面、藉着」"
        }
    },
    "20": {
        "0": {
            "sn": "01163",
            "brief": "应该、必须"
        },
        "1": {
            "sn": "03767",
            "brief": "所以"
        },
        "3": {
            "sn": "04905",
            "brief": "聚集、在一起"
        },
        "4": {
            "sn": "01473",
            "brief": "我"
        },
        "5": {
            "sn": "00435",
            "brief": "丈夫、男人、人"
        },
        "7": {
            "sn": "03956",
            "brief": "所有的、每一个"
        },
        "8": {
            "sn": "05550",
            "brief": "时间"
        },
        "10": {
            "sn": "01525",
            "brief": "进入"
        },
        "11": {
            "sn": "02532",
            "brief": "并且、然后、不必翻译"
        },
        "12": {
            "sn": "01831",
            "brief": "出去"
        },
        "14": {
            "sn": "01473",
            "brief": "我"
        },
        "16": {
            "sn": "02962",
            "brief": "主"
        },
        "17": {
            "sn": "02424",
            "brief": "专有名词，人名：耶稣"
        },
        "9": {
            "sn": "03739",
            "brief": "带出关系子句修饰先行词"
        },
        "2": {
            "sn": "03588",
            "brief": "视情况翻译，有时可译成「这个」、「那个」等"
        },
        "15": {
            "sn": "03588",
            "brief": "视情况翻译，有时可译成「这个」、「那个」等"
        },
        "13": {
            "sn": "01909",
            "brief": "后接直接受格时意思是「在...上面」"
        },
        "6": {
            "sn": "01722",
            "brief": "后接间接受格，意思是「在...里面、藉着」"
        }
    },
    "22": {
        "0": {
            "sn": "02532",
            "brief": "并且、然后、不必翻译"
        },
        "1": {
            "sn": "02476",
            "brief": "选出、提出"
        },
        "2": {
            "sn": "01417",
            "brief": "两个"
        },
        "3": {
            "sn": "02501",
            "brief": "专有名词，人名：约瑟"
        },
        "5": {
            "sn": "02564",
            "brief": "取名、叫"
        },
        "6": {
            "sn": "00923",
            "brief": "专有名词，人名：巴撒巴"
        },
        "8": {
            "sn": "01941",
            "brief": "取名、叫"
        },
        "9": {
            "sn": "02459",
            "brief": "专有名词，人名：犹士都"
        },
        "10": {
            "sn": "02532",
            "brief": "和、并且"
        },
        "11": {
            "sn": "03159",
            "brief": "专有名词，人名：马提亚"
        },
        "7": {
            "sn": "03739",
            "brief": "带出关系子句修饰先行词"
        },
        "4": {
            "sn": "03588",
            "brief": "视情况翻译，有时可译成「这个」、「那个」等"
        }
    },
    "24": {
        "0": {
            "sn": "02983",
            "brief": "领受、接受"
        },
        "2": {
            "sn": "05117",
            "brief": "位置、职分、地方"
        },
        "4": {
            "sn": "01248",
            "brief": "服事、职分"
        },
        "5": {
            "sn": "03778",
            "brief": "这个"
        },
        "6": {
            "sn": "02532",
            "brief": "并且、和"
        },
        "7": {
            "sn": "00651",
            "brief": "使命、使徒的职分"
        },
        "8": {
            "sn": "00575",
            "brief": "后接所有格，意思是「从」"
        },
        "10": {
            "sn": "03845",
            "brief": "放弃、越过"
        },
        "11": {
            "sn": "02455",
            "brief": "专有名词，人名：犹大"
        },
        "12": {
            "sn": "04198",
            "brief": "前进、旅行"
        },
        "13": {
            "sn": "01519",
            "brief": "后接直接受格，意思是「朝向、进入 」"
        },
        "15": {
            "sn": "05117",
            "brief": "地方"
        },
        "17": {
            "sn": "02398",
            "brief": "自己的"
        },
        "9": {
            "sn": "03739",
            "brief": "带出关系子句修饰先行词"
        },
        "1": {
            "sn": "03588",
            "brief": "视情况翻译，有时可译成「这个」、「那个」等"
        },
        "3": {
            "sn": "03588",
            "brief": "视情况翻译，有时可译成「这个」、「那个」等"
        },
        "14": {
            "sn": "03588",
            "brief": "视情况翻译，有时可译成「这个」、「那个」等"
        },
        "16": {
            "sn": "03588",
            "brief": "视情况翻译，有时可译成「这个」、「那个」等"
        }
    },
    "25": {
        "0": {
            "sn": "02532",
            "brief": "然后、不必翻译"
        },
        "1": {
            "sn": "01325",
            "brief": "丢、给、拿出"
        },
        "2": {
            "sn": "02819",
            "brief": "(分发的)一份、签"
        },
        "3": {
            "sn": "00846",
            "brief": "他"
        },
        "4": {
            "sn": "02532",
            "brief": "并且、然后、不必翻译"
        },
        "7": {
            "sn": "02819",
            "brief": "(分发的)一份、签"
        },
        "9": {
            "sn": "03159",
            "brief": "专有名词，人名：马提亚"
        },
        "10": {
            "sn": "02532",
            "brief": "并且、然后、不必翻译"
        },
        "12": {
            "sn": "03326",
            "brief": "后接所有格时意思是「与....一起」"
        },
        "14": {
            "sn": "01733",
            "brief": "十一"
        },
        "15": {
            "sn": "00652",
            "brief": "使徒"
        },
        "6": {
            "sn": "03588",
            "brief": "视情况翻译，有时可译成「这个」、「那个」等"
        },
        "13": {
            "sn": "03588",
            "brief": "视情况翻译，有时可译成「这个」、「那个」等"
        },
        "5": {
            "sn": "04098",
            "brief": "跌倒、掉落"
        },
        "8": {
            "sn": "01909",
            "brief": "后接直接受格时意思是「在...上面」"
        },
        "11": {
            "sn": "04785",
            "brief": "选择使其与...一同、使其与...同列"
        }
    }
}